{
    "type": "pages",
    "headline": "Images",
    "template": {
        "type": "default",
        "layout": "0,0,3,2",
        "color": "msx-glass",
        "imageFiller": "cover",
        "action": "image:context"
    },
    "items": [
        {
            "titleFooter": "Image 1",
            "image": "http://FahadxAi.github.io/data/Left.png"
        },
        {
            "titleFooter": "Image 2",
            "image": "http://FahadxAi.github.io/data/Right.png"
        },
        {
            "titleFooter": "Image 3",
            "image": "http://FahadxAi.github.io/Left.jpg"
        },
        {
            "titleFooter": "Image 4",
            "image": "http://FahadxAi.github.io/Right.jpg"
        }
    ]
}
